coeus_test/__init__.py
coeus_test/assertions.py
coeus_test/client.py
coeus_test/commands.py
coeus_test/message.py
coeus_test/port_forwarding.py
coeus_test-0.1.13.dist-info/LICENSE
coeus_test-0.1.13.dist-info/METADATA
coeus_test-0.1.13.dist-info/WHEEL
coeus_test-0.1.13.dist-info/top_level.txt
coeus_test-0.1.13.dist-info/RECORD
