Metadata-Version: 2.1
Name: coeus-test
Version: 0.1.13
Summary: Python implementation of client protocol for Coeus C# remote integration tests.
Home-page: https://github.com/AgeOfLearning/coeus-python-framework
Author: Devon Klompmaker
Author-email: devon.klompmaker@aofl.com
License: MIT
Keywords: coeus-test
Platform: UNKNOWN
Classifier: Development Status :: 2 - Pre-Alpha
Classifier: Intended Audience :: Developers
Classifier: License :: OSI Approved :: MIT License
Classifier: Natural Language :: English
Classifier: Programming Language :: Python :: 3
Classifier: Programming Language :: Python :: 3.4
Classifier: Programming Language :: Python :: 3.5
Classifier: Programming Language :: Python :: 3.6
Classifier: Programming Language :: Python :: 3.7
